graphene_federation3/__init__.py
graphene_federation3/entity.py
graphene_federation3/entity_query.py
graphene_federation3/extend.py
graphene_federation3/graphene_types.py
graphene_federation3/graphql_compatibility.py
graphene_federation3/main.py
graphene_federation3/provides.py
graphene_federation3/service.py
graphene_federation3/utils.py
graphene_federation3-0.3.3.1687272414.dist-info/LICENSE.txt
graphene_federation3-0.3.3.1687272414.dist-info/METADATA
graphene_federation3-0.3.3.1687272414.dist-info/WHEEL
graphene_federation3-0.3.3.1687272414.dist-info/top_level.txt
graphene_federation3-0.3.3.1687272414.dist-info/RECORD
