Metadata-Version: 2.1
Name: graphene-federation3
Version: 0.3.3.1687272414
Summary: Federation implementation for graphene3
Home-page: https://gitlab.com/live-art-project/graphene-federation3
Author: Yorsh Siarhei
Author-email: myrik260138@gmail.com
License: MIT
Keywords: graphene,gql,federation
Classifier: Development Status :: 5 - Production/Stable
Classifier: Intended Audience :: Developers
Classifier: Topic :: Software Development :: Libraries
Classifier: Programming Language :: Python :: 3.6
License-File: LICENSE.txt
Requires-Dist: graphene (>=3)
Requires-Dist: graphql-core (>=3.1.0)
